README.rst
setup.py
geojsonio/__init__.py
geojsonio/geojsonio.py
geojsonio.egg-info/PKG-INFO
geojsonio.egg-info/SOURCES.txt
geojsonio.egg-info/dependency_links.txt
geojsonio.egg-info/entry_points.txt
geojsonio.egg-info/not-zip-safe
geojsonio.egg-info/requires.txt
geojsonio.egg-info/top_level.txt