Metadata-Version: 1.1
Name: geojsonio
Version: 0.0.1
Summary: geojsonio CLI - Python.
Home-page: https://github.com/jwass/geojsonio.py
Author: Jacob Wasserman
Author-email: jwasserman@gmail.com
License: BSD
Platform: UNKNOWN
Classifier: Intended Audience :: Developers
Classifier: Natural Language :: English
Classifier: License :: OSI Approved :: BSD License
Classifier: Programming Language :: Python :: 2.7
